flower/__init__.py
flower/__main__.py
flower/app.py
flower/command.py
flower/events.py
flower/inspector.py
flower/options.py
flower/urls.py
flower/api/__init__.py
flower/api/control.py
flower/api/tasks.py
flower/api/workers.py
flower/static/favicon.ico
flower/static/swagger.json
flower/static/css/bootstrap.min.css
flower/static/css/bootstrap.min.css.map
flower/static/css/datatables-1.13.4.min.css
flower/static/css/flower.css
flower/static/js/bootstrap.bundle.min.js
flower/static/js/bootstrap.bundle.min.js.map
flower/static/js/datatables-1.13.4.min.js
flower/static/js/flower.js
flower/static/js/jquery-3.6.4.min.js
flower/static/js/jquery-3.6.4.min.map
flower/static/js/moment-2.29.4.min.js
flower/static/js/moment-timezone-with-data-2.29.4.min.js
flower/templates/404.html
flower/templates/base.html
flower/templates/broker.html
flower/templates/error.html
flower/templates/navbar.html
flower/templates/task.html
flower/templates/tasks.html
flower/templates/worker.html
flower/templates/workers.html
flower/utils/__init__.py
flower/utils/broker.py
flower/utils/search.py
flower/utils/tasks.py
flower/utils/template.py
flower/views/__init__.py
flower/views/auth.py
flower/views/broker.py
flower/views/error.py
flower/views/monitor.py
flower/views/tasks.py
flower/views/workers.py
flower-2.0.0.dist-info/LICENSE
flower-2.0.0.dist-info/METADATA
flower-2.0.0.dist-info/WHEEL
flower-2.0.0.dist-info/entry_points.txt
flower-2.0.0.dist-info/top_level.txt
flower-2.0.0.dist-info/RECORD
